d3lta/__init__.py
d3lta/emojis_remover.py
d3lta/faissd3lta.py
d3lta-1.0.2.dist-info/LICENSE.txt
d3lta-1.0.2.dist-info/METADATA
d3lta-1.0.2.dist-info/WHEEL
d3lta-1.0.2.dist-info/RECORD
