Metadata-Version: 2.3
Name: d3lta
Version: 1.0.2
Summary: A library for detecting verbatim-duplicated contents within a vast amount of documents
Author: Viginum
Requires-Python: >=3.10,<4.0
Classifier: Programming Language :: Python :: 3
Classifier: Programming Language :: Python :: 3.10
Classifier: Programming Language :: Python :: 3.11
Classifier: Programming Language :: Python :: 3.12
Classifier: Programming Language :: Python :: 3.13
Requires-Dist: demoji (>=1.1.0,<2.0.0)
Requires-Dist: faiss-cpu (==1.9.0.post1)
Requires-Dist: fasttext (==0.9.3)
Requires-Dist: gensim (==4.3.3)
Requires-Dist: networkx (==2.8.8)
Requires-Dist: pandas (==2.2.3)
Requires-Dist: polyleven (==0.8)
Requires-Dist: scipy (==1.12.0)
Requires-Dist: tensorflow (==2.18.0)
Requires-Dist: tensorflow-hub (==0.16.1)
Requires-Dist: tensorflow-text (==2.18.1)
Requires-Dist: tqdm (==4.67.1)
